econmodels/__init__.py
econmodels/adstock.py
econmodels/decomp.py
econmodels/features.py
econmodels/misc.py
econmodels/models.py
econmodels-0.1.dist-info/METADATA
econmodels-0.1.dist-info/WHEEL
econmodels-0.1.dist-info/top_level.txt
econmodels-0.1.dist-info/RECORD
